pyExSi/__init__.py
pyExSi/signals.py
pyexsi-0.43.3.dist-info/METADATA
pyexsi-0.43.3.dist-info/WHEEL
pyexsi-0.43.3.dist-info/licenses/LICENSE
pyexsi-0.43.3.dist-info/RECORD
