Metadata-Version: 2.4
Name: pyExSi
Version: 0.43.3
Summary: Excitation signals as used in structural dynamics and vibration fatigue.
Project-URL: homepage, https://github.com/ladisk/pyExSi
Project-URL: documentation, https://pyexsi.readthedocs.io/en/latest/index.html
Project-URL: source, https://github.com/sdypy/pyExSi
Author-email: "Aleš Zorman, Domen Gorjup, Janko Slavič" <janko.slavic@fs.uni-lj.si>
Maintainer-email: "Janko Slavič, Domen Gorjup, Aleš Zorman" <janko.slavic@fs.uni-lj.si>
License-Expression: MIT
License-File: LICENSE
Keywords: dynamic testing,excitation signal,structural dynamics
Classifier: Development Status :: 3 - Alpha
Classifier: Intended Audience :: Developers
Classifier: License :: OSI Approved :: MIT License
Classifier: Programming Language :: Python :: 3.10
Classifier: Topic :: Scientific/Engineering
Requires-Python: >=3.10
Requires-Dist: numpy>=1.18
Requires-Dist: pylint
Requires-Dist: pytest
Requires-Dist: scipy
Provides-Extra: dev
Requires-Dist: black; extra == 'dev'
Requires-Dist: build; extra == 'dev'
Requires-Dist: matplotlib; extra == 'dev'
Requires-Dist: pytest; extra == 'dev'
Requires-Dist: sphinx; extra == 'dev'
Requires-Dist: sphinx-copybutton>=0.5.2; extra == 'dev'
Requires-Dist: sphinx-rtd-theme; extra == 'dev'
Requires-Dist: twine; extra == 'dev'
Requires-Dist: wheel; extra == 'dev'
